scintillometry/__init__.py
scintillometry/main.py
scintillometry/backend/__init__.py
scintillometry/backend/constants.py
scintillometry/backend/constructions.py
scintillometry/backend/deprecations.py
scintillometry/backend/derivations.py
scintillometry/backend/iterations.py
scintillometry/backend/transects.py
scintillometry/metrics/__init__.py
scintillometry/metrics/calculations.py
scintillometry/visuals/__init__.py
scintillometry/visuals/plotting.py
scintillometry/wrangler/__init__.py
scintillometry/wrangler/data_parser.py
scintillometry-1.0.5.dist-info/METADATA
scintillometry-1.0.5.dist-info/WHEEL
scintillometry-1.0.5.dist-info/licenses/LICENSE
scintillometry-1.0.5.dist-info/RECORD
