Metadata-Version: 2.1
Name: scintillometry
Version: 1.0.5
Summary: Analyse data & 2D flux footprints from Scintec's BLS scintillometers.
Project-URL: Homepage, https://github.com/gampnico/scintillometry
Project-URL: Bug Tracker, https://github.com/gampnico/scintillometry/issues
Project-URL: Documentation, https://scintillometry.readthedocs.io/en/latest/
Author: Scintillometry Contributors
License-Expression: Apache-2.0
License-File: LICENSE
Classifier: Development Status :: 4 - Beta
Classifier: Environment :: Console
Classifier: License :: OSI Approved :: Apache Software License
Classifier: Operating System :: POSIX :: Linux
Classifier: Programming Language :: Python :: 3.8
Classifier: Programming Language :: Python :: 3.9
Classifier: Programming Language :: Python :: 3.10
Classifier: Programming Language :: Python :: 3.11
Classifier: Topic :: Scientific/Engineering :: Atmospheric Science
Classifier: Topic :: Scientific/Engineering :: Information Analysis
Requires-Python: >=3.8
Requires-Dist: kneed
Requires-Dist: matplotlib
Requires-Dist: mpmath>=1.2.1
Requires-Dist: numpy
Requires-Dist: pandas>=2.0
Requires-Dist: scikit-learn
Requires-Dist: scipy>=1.10
Requires-Dist: tqdm>4.8
Provides-Extra: dev
Requires-Dist: black>=23.1; extra == 'dev'
Requires-Dist: build>=0.7; extra == 'dev'
Requires-Dist: flake8>=6.0; extra == 'dev'
Requires-Dist: hatchling>=1.12; extra == 'dev'
Requires-Dist: isort; extra == 'dev'
Requires-Dist: pylint>=2.16.1; extra == 'dev'
Requires-Dist: scintillometry[docs,tests]; extra == 'dev'
Provides-Extra: docs
Requires-Dist: sphinx; extra == 'docs'
Requires-Dist: sphinx-rtd-theme>=1.1; extra == 'docs'
Provides-Extra: tests
Requires-Dist: coverage>=7.1; extra == 'tests'
Requires-Dist: pytest-dependency>=0.5; extra == 'tests'
Requires-Dist: pytest>=7.0; extra == 'tests'
